{
  "type": "create:splashing",
  "ingredients": [
    {
      "item": "create:crushed_raw_silver"
    }
  ],
  "results": [
    {
      "item": "create_unify:silver_nugget",
      "count": 9
    },
    {
      "item": "minecraft:glowstone_dust",
      "chance": 0.35
    }
  ],

  "conditions": [
    {
      "type": "forge:not",
      "value": [
        {
          "type": "forge:tag_empty",
          "tag": "create_unify:enable_features"
        },
        {
          "type": "forge:tag_empty",
          "tag": "forge:raw_materials/silver"
        }
      ]
    }
  ]
}